CETEMPublico/__init__.py
CETEMPublico/corpus.py
cetem_publico-0.0.16.dist-info/LICENSE.rst
cetem_publico-0.0.16.dist-info/METADATA
cetem_publico-0.0.16.dist-info/WHEEL
cetem_publico-0.0.16.dist-info/top_level.txt
cetem_publico-0.0.16.dist-info/RECORD
