Metadata-Version: 2.1
Name: cetem-publico
Version: 0.0.16
Summary: Python wrapper for the CETEMPublico corpus
Home-page: https://github.com/andrefs/cetem_publico
Author: André Santos
Author-email: afs@inesctec.pt
License: UNKNOWN
Project-URL: Bug Reports, https://github.com/andrefs/cetem_publico/issues
Project-URL: Source, https://github.com/andrefs/cetem_publico/
Platform: UNKNOWN
Requires-Dist: clint
